HISTORY.txt
MANIFEST.in
README.rst
bootstrap.py
buildout.cfg
setup.py
Products/__init__.py
Products/__init__.pyc
Products.ifQuotes.egg-info/PKG-INFO
Products.ifQuotes.egg-info/SOURCES.txt
Products.ifQuotes.egg-info/dependency_links.txt
Products.ifQuotes.egg-info/namespace_packages.txt
Products.ifQuotes.egg-info/requires.txt
Products.ifQuotes.egg-info/top_level.txt
Products/ifQuotes/__init__.py
Products/ifQuotes/config.py
Products/ifQuotes/configure.zcml
Products/ifQuotes/profiles.zcml
Products/ifQuotes/refresh.txt
Products/ifQuotes/setuphandlers.py
Products/ifQuotes/version.txt
Products/ifQuotes/browser/__init__.py
Products/ifQuotes/browser/configure.zcml
Products/ifQuotes/browser/quote.py
Products/ifQuotes/browser/templates/quote_view.pt
Products/ifQuotes/content/Quote.py
Products/ifQuotes/content/QuoteFolder.py
Products/ifQuotes/content/__init__.py
Products/ifQuotes/content/interfaces.py
Products/ifQuotes/model/ifQuotes.zargo
Products/ifQuotes/portlets/__init__.py
Products/ifQuotes/portlets/configure.zcml
Products/ifQuotes/portlets/quotes.py
Products/ifQuotes/portlets/templates/randomquote.pt
Products/ifQuotes/profiles/default/cssregistry.xml
Products/ifQuotes/profiles/default/factorytool.xml
Products/ifQuotes/profiles/default/ifQuotes_marker.txt
Products/ifQuotes/profiles/default/import_steps.xml
Products/ifQuotes/profiles/default/jsregistry.xml
Products/ifQuotes/profiles/default/portlets.xml
Products/ifQuotes/profiles/default/skins.xml
Products/ifQuotes/profiles/default/types.xml
Products/ifQuotes/profiles/default/types/Quote.xml
Products/ifQuotes/profiles/default/types/QuoteFolder.xml
Products/ifQuotes/skins/ifquotes_images/Quote.gif
Products/ifQuotes/skins/ifquotes_images/QuoteFolder.gif
Products/ifQuotes/tests/__init__.py
Products/ifQuotes/tests/base.py
Products/ifQuotes/tests/test_doctest.py
Products/ifQuotes/tests/test_portlet_promotions.py