Metadata-Version: 1.0
Name: Products.ifQuotes
Version: 1.0.2
Summary: A 'quote' content type for Plone
Home-page: https://github.com/collective/Products.ifQuotes
Author: Alex Clark
Author-email: aclark@aclark.net
License: UNKNOWN
Platform: UNKNOWN
